feast_teradata/__init__.py
feast_teradata/teradata_utils.py
feast_teradata/cli/__init__.py
feast_teradata/cli/cli.py
feast_teradata/cli/template/teradata/bootstrap.py
feast_teradata/cli/template/teradata/test_workflow.py
feast_teradata/cli/template/teradata/feature_repo/driver_repo.py
feast_teradata/cli/template/teradata/feature_repo/feature_store.yaml
feast_teradata/offline/__init__.py
feast_teradata/offline/teradata.py
feast_teradata/offline/teradata_source.py
feast_teradata/online/__init__.py
feast_teradata/online/teradata.py
feast_teradata-1.0.4.dist-info/LICENSE
feast_teradata-1.0.4.dist-info/LICENSE-3RD-PARTY.txt
feast_teradata-1.0.4.dist-info/METADATA
feast_teradata-1.0.4.dist-info/WHEEL
feast_teradata-1.0.4.dist-info/entry_points.txt
feast_teradata-1.0.4.dist-info/top_level.txt
feast_teradata-1.0.4.dist-info/RECORD
