Metadata-Version: 2.1
Name: feast-teradata
Version: 1.0.4
Summary: UNKNOWN
Home-page: https://github.com/Teradata/feast-teradata
Author: Teradata Corporation
Author-email: developers@teradata.com
License: UNKNOWN
Platform: UNKNOWN
Requires-Python: >=3.8,<3.11
License-File: LICENSE
License-File: LICENSE-3RD-PARTY.txt
Requires-Dist: teradataml (>=17.0.0.4)
Requires-Dist: feast (==0.31.1)
